<?xml version="1.0" encoding="UTF-8"?>
<objects serializationModel="Studio.02.02.00">
	<object class="AudioFile" id="{7dc2f14f-3b69-45ee-a363-afd2eb0fd3b3}">
		<property name="assetPath">
			<value>Diablo II Sounds/monster/Minion/neutral1.wav</value>
		</property>
		<property name="frequencyInKHz">
			<value>22.0499992</value>
		</property>
		<property name="channelCount">
			<value>1</value>
		</property>
		<property name="length">
			<value>0.21551020408163266</value>
		</property>
		<relationship name="masterAssetFolder">
			<destination>{f9f4e14a-4e4b-4f40-a5a4-f26cdf67b796}</destination>
		</relationship>
	</object>
</objects>
