<?xml version="1.0" encoding="UTF-8"?>
<objects serializationModel="Studio.02.02.00">
	<object class="AudioFile" id="{96ee615f-f2a2-4b87-ad87-eca6234e1438}">
		<property name="assetPath">
			<value>Diablo II Sounds/ambient/Event/thunder_norm_1.wav</value>
		</property>
		<property name="frequencyInKHz">
			<value>22.0499992</value>
		</property>
		<property name="channelCount">
			<value>1</value>
		</property>
		<property name="length">
			<value>6.1881179138321993</value>
		</property>
		<relationship name="masterAssetFolder">
			<destination>{f9f4e14a-4e4b-4f40-a5a4-f26cdf67b796}</destination>
		</relationship>
	</object>
</objects>
