<?xml version="1.0" encoding="UTF-8"?>
<objects serializationModel="Studio.02.02.00">
	<object class="AudioFile" id="{b3d8423e-b8aa-42d6-a8c9-3ca9ed7ec889}">
		<property name="assetPath">
			<value>Diablo II Sounds/monster/DruidBear/gethit08.wav</value>
		</property>
		<property name="frequencyInKHz">
			<value>22.0499992</value>
		</property>
		<property name="channelCount">
			<value>1</value>
		</property>
		<property name="length">
			<value>0.41569160997732424</value>
		</property>
		<relationship name="masterAssetFolder">
			<destination>{f9f4e14a-4e4b-4f40-a5a4-f26cdf67b796}</destination>
		</relationship>
	</object>
</objects>
